{
  "features": [
    {
      "geometry": {
        "coordinates": [
          -120.69707273253104,
          37.665446025378436
        ],
        "type": "Point"
      },
      "type": "Feature",
      "properties": {
        "Description": "3700, 500",
        "Name": "Ribeiro"
      }
    },
    {
      "geometry": {
        "coordinates": [
          [
            [
              -120.7032125413734,
              37.67101486474843
            ],
            [
              -120.7031364209059,
              37.67139754818079
            ],
            [
              -120.70291964815459,
              37.671721971529614
            ],
            [
              -120.70268393811023,
              37.67189678601278
            ],
            [
              -120.70231055851373,
              37.6720100494751
            ],
            [
              -120.69193326982821,
              37.67201486474843
            ],
            [
              -120.69155058639585,
              37.67193874428094
            ],
            [
              -120.69122616304702,
              37.671721971529614
            ],
            [
              -120.6910093902957,
              37.67139754818079
            ],
            [
              -120.69093326982821,
              37.67101486474843
            ],
            [
              -120.69093326982821,
              37.65987898724103
            ],
            [
              -120.6910093902957,
              37.659496303808666
            ],
            [
              -120.69122616304702,
              37.659171880459844
            ],
            [
              -120.69155058639585,
              37.658955107708515
            ],
            [
              -120.69193326982821,
              37.65887898724103
            ],
            [
              -120.7022125413734,
              37.65887898724103
            ],
            [
              -120.70259522480576,
              37.658955107708515
            ],
            [
              -120.70291964815459,
              37.659171880459844
            ],
            [
              -120.7031364209059,
              37.659496303808666
            ],
            [
              -120.7032125413734,
              37.65987898724103
            ],
            [
              -120.7032125413734,
              37.67101486474843
            ]
          ]
        ],
        "type": "Polygon"
      },
      "type": "Feature",
      "properties": {
        "Description": "",
        "Name": "Ribeiro"
      }
    },
    {
      "geometry": {
        "coordinates": [
          -120.97928436163546,
          37.738084211710294
        ],
        "type": "Point"
      },
      "type": "Feature",
      "properties": {
        "Description": "3600, 500",
        "Name": "Ribeiro Patterson"
      }
    },
    {
      "geometry": {
        "coordinates": [
          [
            [
              -120.98278007909849,
              37.740009799151835
            ],
            [
              -120.98270395863099,
              37.7403924825842
            ],
            [
              -120.98248718587968,
              37.74071690593302
            ],
            [
              -120.98225147583531,
              37.74089172041619
            ],
            [
              -120.98187809623882,
              37.741004983878504
            ],
            [
              -120.97678615365038,
              37.74100979915183
            ],
            [
              -120.97623058341736,
              37.740841268764136
            ],
            [
              -120.97595468403807,
              37.74056536938485
            ],
            [
              -120.9757909689237,
              37.740107816292166
            ],
            [
              -120.97578615365038,
              37.73615800834534
            ],
            [
              -120.97595468403807,
              37.73560243811232
            ],
            [
              -120.97631475691355,
              37.73527608708099
            ],
            [
              -120.97678615365038,
              37.735158008345344
            ],
            [
              -120.98178007909848,
              37.735158008345344
            ],
            [
              -120.9823356493315,
              37.73532653873304
            ],
            [
              -120.98261154871079,
              37.73560243811232
            ],
            [
              -120.98277526382516,
              37.73605999120501
            ],
            [
              -120.98278007909849,
              37.740009799151835
            ]
          ]
        ],
        "type": "Polygon"
      },
      "type": "Feature",
      "properties": {
        "Description": "",
        "Name": "Ribeiro Patterson"
      }
    }
  ],
  "type": "FeatureCollection",
  "crs": {
    "type": "name",
    "properties": {
      "name": "urn:ogc:def:crs:OGC:1.3:CRS84"
    }
  }
}